[
  {
    "uid": "e10957f6",
    "url": "https://smartstore.naver.com/euromarkt/products/8670482219",
    "brand": "하리보",
    "qtys": [
      3,
      5,
      8,
      10,
      12,
      15
    ],
    "min_qty": 3,
    "volume": 0.0,
    "volume_unit": "L",
    "use_nobg": false,
    "draft": false,
    "gtin": "",
    "source_file": "하리보.txt",
    "gosisi_cat": "기타 재화",
    "category_id": "79578",
    "category_is_manual": false,
    "qty_locked": false,
    "naver_price": 3600,
    "manual_options": [],
    "lead_time": 10,
    "single_mode": false,
    "single_selected_imgs": [],
    "margin_override": 0.0,
    "watch_store": "제니스 트레이딩",
    "price_extra": 0,
    "extra_detail_images": [],
    "extra_detail_text": "",
    "status": "done"
  },
  {
    "uid": "6e26b8fc",
    "url": "https://smartstore.naver.com/euromarkt/products/8670502491",
    "brand": "하리보",
    "qtys": [
      3,
      5,
      8,
      10,
      12,
      15
    ],
    "min_qty": 3,
    "volume": 0.0,
    "volume_unit": "L",
    "use_nobg": false,
    "draft": false,
    "gtin": "",
    "source_file": "하리보.txt",
    "gosisi_cat": "기타 재화",
    "category_id": "79578",
    "category_is_manual": false,
    "qty_locked": false,
    "naver_price": 3600,
    "manual_options": [],
    "lead_time": 10,
    "single_mode": false,
    "single_selected_imgs": [],
    "margin_override": 0.0,
    "watch_store": "제니스 트레이딩",
    "price_extra": 0,
    "extra_detail_images": [],
    "extra_detail_text": "",
    "status": "done"
  },
  {
    "uid": "8cd6a47b",
    "url": "https://smartstore.naver.com/euromarkt/products/8670483546",
    "brand": "하리보",
    "qtys": [
      3,
      5,
      8,
      10,
      12,
      15
    ],
    "min_qty": 3,
    "volume": 0.0,
    "volume_unit": "L",
    "use_nobg": false,
    "draft": false,
    "gtin": "",
    "source_file": "하리보.txt",
    "gosisi_cat": "기타 재화",
    "category_id": "79578",
    "category_is_manual": false,
    "qty_locked": false,
    "naver_price": 3600,
    "manual_options": [],
    "lead_time": 10,
    "single_mode": false,
    "single_selected_imgs": [],
    "margin_override": 0.0,
    "watch_store": "제니스 트레이딩",
    "price_extra": 0,
    "extra_detail_images": [],
    "extra_detail_text": "",
    "status": "done"
  },
  {
    "uid": "a87ced28",
    "url": "https://smartstore.naver.com/euromarkt/products/10972097790",
    "brand": "하리보",
    "qtys": [
      3,
      5,
      8,
      10,
      12,
      15
    ],
    "min_qty": 3,
    "volume": 0.0,
    "volume_unit": "L",
    "use_nobg": false,
    "draft": false,
    "gtin": "",
    "source_file": "하리보.txt",
    "gosisi_cat": "기타 재화",
    "category_id": "79578",
    "category_is_manual": false,
    "qty_locked": false,
    "naver_price": 3600,
    "manual_options": [],
    "lead_time": 10,
    "single_mode": false,
    "single_selected_imgs": [],
    "margin_override": 0.0,
    "watch_store": "제니스 트레이딩",
    "price_extra": 0,
    "extra_detail_images": [],
    "extra_detail_text": "",
    "status": "done"
  },
  {
    "uid": "1e9e4e21",
    "url": "https://smartstore.naver.com/euromarkt/products/8670494891",
    "brand": "HARIBO",
    "qtys": [
      3,
      5,
      8,
      10,
      12,
      15
    ],
    "min_qty": 3,
    "volume": 0.0,
    "volume_unit": "L",
    "use_nobg": false,
    "draft": false,
    "gtin": "",
    "source_file": "하리보.txt",
    "gosisi_cat": "기타 재화",
    "category_id": "79578",
    "category_is_manual": false,
    "qty_locked": false,
    "naver_price": 3600,
    "manual_options": [],
    "lead_time": 10,
    "single_mode": false,
    "single_selected_imgs": [],
    "margin_override": 0.0,
    "watch_store": "제니스 트레이딩",
    "price_extra": 0,
    "extra_detail_images": [],
    "extra_detail_text": "",
    "status": "done"
  },
  {
    "uid": "25669120",
    "url": "https://smartstore.naver.com/euromarkt/products/8670500678",
    "brand": "HARIBO",
    "qtys": [
      3,
      5,
      8,
      10,
      12,
      15
    ],
    "min_qty": 3,
    "volume": 0.0,
    "volume_unit": "L",
    "use_nobg": false,
    "draft": false,
    "gtin": "",
    "source_file": "하리보.txt",
    "gosisi_cat": "기타 재화",
    "category_id": "79578",
    "category_is_manual": false,
    "qty_locked": false,
    "naver_price": 3600,
    "manual_options": [],
    "lead_time": 10,
    "single_mode": false,
    "single_selected_imgs": [],
    "margin_override": 0.0,
    "watch_store": "제니스 트레이딩",
    "price_extra": 0,
    "extra_detail_images": [],
    "extra_detail_text": "",
    "status": "done"
  },
  {
    "uid": "c3a846a0",
    "url": "https://smartstore.naver.com/euromarkt/products/8670490137",
    "brand": "",
    "qtys": [
      3,
      5,
      8,
      10,
      12,
      15
    ],
    "min_qty": 3,
    "volume": 0.0,
    "volume_unit": "L",
    "use_nobg": false,
    "draft": false,
    "gtin": "",
    "source_file": "하리보.txt",
    "gosisi_cat": "기타 재화",
    "category_id": "",
    "category_is_manual": false,
    "qty_locked": false,
    "naver_price": 0,
    "manual_options": [],
    "lead_time": 10,
    "single_mode": false,
    "single_selected_imgs": [],
    "margin_override": 0.0,
    "watch_store": "제니스 트레이딩",
    "price_extra": 0,
    "extra_detail_images": [],
    "extra_detail_text": "",
    "status": "processing"
  },
  {
    "uid": "b8613f32",
    "url": "https://smartstore.naver.com/euromarkt/products/8670504228",
    "brand": "",
    "qtys": [
      3,
      5,
      8,
      10,
      12,
      15
    ],
    "min_qty": 3,
    "volume": 0.0,
    "volume_unit": "L",
    "use_nobg": false,
    "draft": false,
    "gtin": "",
    "source_file": "하리보.txt",
    "gosisi_cat": "기타 재화",
    "category_id": "",
    "category_is_manual": false,
    "qty_locked": false,
    "naver_price": 0,
    "manual_options": [],
    "lead_time": 10,
    "single_mode": false,
    "single_selected_imgs": [],
    "margin_override": 0.0,
    "watch_store": "제니스 트레이딩",
    "price_extra": 0,
    "extra_detail_images": [],
    "extra_detail_text": "",
    "status": "pending"
  },
  {
    "uid": "f5b16694",
    "url": "https://smartstore.naver.com/euromarkt/products/8670480315",
    "brand": "",
    "qtys": [
      3,
      5,
      8,
      10,
      12,
      15
    ],
    "min_qty": 3,
    "volume": 0.0,
    "volume_unit": "L",
    "use_nobg": false,
    "draft": false,
    "gtin": "",
    "source_file": "하리보.txt",
    "gosisi_cat": "기타 재화",
    "category_id": "",
    "category_is_manual": false,
    "qty_locked": false,
    "naver_price": 0,
    "manual_options": [],
    "lead_time": 10,
    "single_mode": false,
    "single_selected_imgs": [],
    "margin_override": 0.0,
    "watch_store": "제니스 트레이딩",
    "price_extra": 0,
    "extra_detail_images": [],
    "extra_detail_text": "",
    "status": "pending"
  },
  {
    "uid": "fb359361",
    "url": "https://smartstore.naver.com/euromarkt/products/11900761851",
    "brand": "",
    "qtys": [
      3,
      5,
      8,
      10,
      12,
      15
    ],
    "min_qty": 3,
    "volume": 0.0,
    "volume_unit": "L",
    "use_nobg": false,
    "draft": false,
    "gtin": "",
    "source_file": "하리보.txt",
    "gosisi_cat": "기타 재화",
    "category_id": "",
    "category_is_manual": false,
    "qty_locked": false,
    "naver_price": 0,
    "manual_options": [],
    "lead_time": 10,
    "single_mode": false,
    "single_selected_imgs": [],
    "margin_override": 0.0,
    "watch_store": "제니스 트레이딩",
    "price_extra": 0,
    "extra_detail_images": [],
    "extra_detail_text": "",
    "status": "pending"
  },
  {
    "uid": "5ea06eb5",
    "url": "https://smartstore.naver.com/euromarkt/products/11385969008",
    "brand": "",
    "qtys": [
      3,
      5,
      8,
      10,
      12,
      15
    ],
    "min_qty": 3,
    "volume": 0.0,
    "volume_unit": "L",
    "use_nobg": false,
    "draft": false,
    "gtin": "",
    "source_file": "하리보.txt",
    "gosisi_cat": "기타 재화",
    "category_id": "",
    "category_is_manual": false,
    "qty_locked": false,
    "naver_price": 0,
    "manual_options": [],
    "lead_time": 10,
    "single_mode": false,
    "single_selected_imgs": [],
    "margin_override": 0.0,
    "watch_store": "제니스 트레이딩",
    "price_extra": 0,
    "extra_detail_images": [],
    "extra_detail_text": "",
    "status": "pending"
  },
  {
    "uid": "ff116f06",
    "url": "https://smartstore.naver.com/euromarkt/products/11002995372",
    "brand": "",
    "qtys": [
      3,
      5,
      8,
      10,
      12,
      15
    ],
    "min_qty": 3,
    "volume": 0.0,
    "volume_unit": "L",
    "use_nobg": false,
    "draft": false,
    "gtin": "",
    "source_file": "하리보.txt",
    "gosisi_cat": "기타 재화",
    "category_id": "",
    "category_is_manual": false,
    "qty_locked": false,
    "naver_price": 0,
    "manual_options": [],
    "lead_time": 10,
    "single_mode": false,
    "single_selected_imgs": [],
    "margin_override": 0.0,
    "watch_store": "제니스 트레이딩",
    "price_extra": 0,
    "extra_detail_images": [],
    "extra_detail_text": "",
    "status": "pending"
  },
  {
    "uid": "66e91c70",
    "url": "https://smartstore.naver.com/euromarkt/products/10972097380",
    "brand": "",
    "qtys": [
      3,
      5,
      8,
      10,
      12,
      15
    ],
    "min_qty": 3,
    "volume": 0.0,
    "volume_unit": "L",
    "use_nobg": false,
    "draft": false,
    "gtin": "",
    "source_file": "하리보.txt",
    "gosisi_cat": "기타 재화",
    "category_id": "",
    "category_is_manual": false,
    "qty_locked": false,
    "naver_price": 0,
    "manual_options": [],
    "lead_time": 10,
    "single_mode": false,
    "single_selected_imgs": [],
    "margin_override": 0.0,
    "watch_store": "제니스 트레이딩",
    "price_extra": 0,
    "extra_detail_images": [],
    "extra_detail_text": "",
    "status": "pending"
  },
  {
    "uid": "cfdcde82",
    "url": "https://smartstore.naver.com/euromarkt/products/10972095754",
    "brand": "",
    "qtys": [
      3,
      5,
      8,
      10,
      12,
      15
    ],
    "min_qty": 3,
    "volume": 0.0,
    "volume_unit": "L",
    "use_nobg": false,
    "draft": false,
    "gtin": "",
    "source_file": "하리보.txt",
    "gosisi_cat": "기타 재화",
    "category_id": "",
    "category_is_manual": false,
    "qty_locked": false,
    "naver_price": 0,
    "manual_options": [],
    "lead_time": 10,
    "single_mode": false,
    "single_selected_imgs": [],
    "margin_override": 0.0,
    "watch_store": "제니스 트레이딩",
    "price_extra": 0,
    "extra_detail_images": [],
    "extra_detail_text": "",
    "status": "pending"
  },
  {
    "uid": "dab09d1e",
    "url": "https://smartstore.naver.com/euromarkt/products/9259509678",
    "brand": "",
    "qtys": [
      3,
      5,
      8,
      10,
      12,
      15
    ],
    "min_qty": 3,
    "volume": 0.0,
    "volume_unit": "L",
    "use_nobg": false,
    "draft": false,
    "gtin": "",
    "source_file": "하리보.txt",
    "gosisi_cat": "기타 재화",
    "category_id": "",
    "category_is_manual": false,
    "qty_locked": false,
    "naver_price": 0,
    "manual_options": [],
    "lead_time": 10,
    "single_mode": false,
    "single_selected_imgs": [],
    "margin_override": 0.0,
    "watch_store": "제니스 트레이딩",
    "price_extra": 0,
    "extra_detail_images": [],
    "extra_detail_text": "",
    "status": "pending"
  },
  {
    "uid": "e32af00d",
    "url": "https://smartstore.naver.com/euromarkt/products/8670496926",
    "brand": "",
    "qtys": [
      3,
      5,
      8,
      10,
      12,
      15
    ],
    "min_qty": 3,
    "volume": 0.0,
    "volume_unit": "L",
    "use_nobg": false,
    "draft": false,
    "gtin": "",
    "source_file": "하리보.txt",
    "gosisi_cat": "기타 재화",
    "category_id": "",
    "category_is_manual": false,
    "qty_locked": false,
    "naver_price": 0,
    "manual_options": [],
    "lead_time": 10,
    "single_mode": false,
    "single_selected_imgs": [],
    "margin_override": 0.0,
    "watch_store": "제니스 트레이딩",
    "price_extra": 0,
    "extra_detail_images": [],
    "extra_detail_text": "",
    "status": "pending"
  },
  {
    "uid": "5f4d7fe3",
    "url": "https://smartstore.naver.com/euromarkt/products/12773574661",
    "brand": "",
    "qtys": [
      3,
      5,
      8,
      10,
      12,
      15
    ],
    "min_qty": 3,
    "volume": 0.0,
    "volume_unit": "L",
    "use_nobg": false,
    "draft": false,
    "gtin": "",
    "source_file": "하리보.txt",
    "gosisi_cat": "기타 재화",
    "category_id": "",
    "category_is_manual": false,
    "qty_locked": false,
    "naver_price": 0,
    "manual_options": [],
    "lead_time": 10,
    "single_mode": false,
    "single_selected_imgs": [],
    "margin_override": 0.0,
    "watch_store": "제니스 트레이딩",
    "price_extra": 0,
    "extra_detail_images": [],
    "extra_detail_text": "",
    "status": "pending"
  },
  {
    "uid": "45de33cf",
    "url": "https://smartstore.naver.com/euromarkt/products/10972096748",
    "brand": "",
    "qtys": [
      3,
      5,
      8,
      10,
      12,
      15
    ],
    "min_qty": 3,
    "volume": 0.0,
    "volume_unit": "L",
    "use_nobg": false,
    "draft": false,
    "gtin": "",
    "source_file": "하리보.txt",
    "gosisi_cat": "기타 재화",
    "category_id": "",
    "category_is_manual": false,
    "qty_locked": false,
    "naver_price": 0,
    "manual_options": [],
    "lead_time": 10,
    "single_mode": false,
    "single_selected_imgs": [],
    "margin_override": 0.0,
    "watch_store": "제니스 트레이딩",
    "price_extra": 0,
    "extra_detail_images": [],
    "extra_detail_text": "",
    "status": "pending"
  },
  {
    "uid": "f6149c16",
    "url": "https://smartstore.naver.com/euromarkt/products/8670500155",
    "brand": "",
    "qtys": [
      3,
      5,
      8,
      10,
      12,
      15
    ],
    "min_qty": 3,
    "volume": 0.0,
    "volume_unit": "L",
    "use_nobg": false,
    "draft": false,
    "gtin": "",
    "source_file": "하리보.txt",
    "gosisi_cat": "기타 재화",
    "category_id": "",
    "category_is_manual": false,
    "qty_locked": false,
    "naver_price": 0,
    "manual_options": [],
    "lead_time": 10,
    "single_mode": false,
    "single_selected_imgs": [],
    "margin_override": 0.0,
    "watch_store": "제니스 트레이딩",
    "price_extra": 0,
    "extra_detail_images": [],
    "extra_detail_text": "",
    "status": "pending"
  },
  {
    "uid": "d4275bdc",
    "url": "https://smartstore.naver.com/euromarkt/products/8670489434",
    "brand": "",
    "qtys": [
      3,
      5,
      8,
      10,
      12,
      15
    ],
    "min_qty": 3,
    "volume": 0.0,
    "volume_unit": "L",
    "use_nobg": false,
    "draft": false,
    "gtin": "",
    "source_file": "하리보.txt",
    "gosisi_cat": "기타 재화",
    "category_id": "",
    "category_is_manual": false,
    "qty_locked": false,
    "naver_price": 0,
    "manual_options": [],
    "lead_time": 10,
    "single_mode": false,
    "single_selected_imgs": [],
    "margin_override": 0.0,
    "watch_store": "제니스 트레이딩",
    "price_extra": 0,
    "extra_detail_images": [],
    "extra_detail_text": "",
    "status": "pending"
  },
  {
    "uid": "6816c026",
    "url": "https://smartstore.naver.com/euromarkt/products/8670475056",
    "brand": "",
    "qtys": [
      3,
      5,
      8,
      10,
      12,
      15
    ],
    "min_qty": 3,
    "volume": 0.0,
    "volume_unit": "L",
    "use_nobg": false,
    "draft": false,
    "gtin": "",
    "source_file": "하리보.txt",
    "gosisi_cat": "기타 재화",
    "category_id": "",
    "category_is_manual": false,
    "qty_locked": false,
    "naver_price": 0,
    "manual_options": [],
    "lead_time": 10,
    "single_mode": false,
    "single_selected_imgs": [],
    "margin_override": 0.0,
    "watch_store": "제니스 트레이딩",
    "price_extra": 0,
    "extra_detail_images": [],
    "extra_detail_text": "",
    "status": "pending"
  },
  {
    "uid": "7c63e388",
    "url": "https://smartstore.naver.com/euromarkt/products/8670474252",
    "brand": "",
    "qtys": [
      3,
      5,
      8,
      10,
      12,
      15
    ],
    "min_qty": 3,
    "volume": 0.0,
    "volume_unit": "L",
    "use_nobg": false,
    "draft": false,
    "gtin": "",
    "source_file": "하리보.txt",
    "gosisi_cat": "기타 재화",
    "category_id": "",
    "category_is_manual": false,
    "qty_locked": false,
    "naver_price": 0,
    "manual_options": [],
    "lead_time": 10,
    "single_mode": false,
    "single_selected_imgs": [],
    "margin_override": 0.0,
    "watch_store": "제니스 트레이딩",
    "price_extra": 0,
    "extra_detail_images": [],
    "extra_detail_text": "",
    "status": "pending"
  },
  {
    "uid": "3cabc981",
    "url": "https://smartstore.naver.com/euromarkt/products/12809682003",
    "brand": "",
    "qtys": [
      3,
      5,
      8,
      10,
      12,
      15
    ],
    "min_qty": 3,
    "volume": 0.0,
    "volume_unit": "L",
    "use_nobg": false,
    "draft": false,
    "gtin": "",
    "source_file": "하리보.txt",
    "gosisi_cat": "기타 재화",
    "category_id": "",
    "category_is_manual": false,
    "qty_locked": false,
    "naver_price": 0,
    "manual_options": [],
    "lead_time": 10,
    "single_mode": false,
    "single_selected_imgs": [],
    "margin_override": 0.0,
    "watch_store": "제니스 트레이딩",
    "price_extra": 0,
    "extra_detail_images": [],
    "extra_detail_text": "",
    "status": "pending"
  },
  {
    "uid": "2f0b261f",
    "url": "https://smartstore.naver.com/euromarkt/products/11871762895",
    "brand": "",
    "qtys": [
      3,
      5,
      8,
      10,
      12,
      15
    ],
    "min_qty": 3,
    "volume": 0.0,
    "volume_unit": "L",
    "use_nobg": false,
    "draft": false,
    "gtin": "",
    "source_file": "하리보.txt",
    "gosisi_cat": "기타 재화",
    "category_id": "",
    "category_is_manual": false,
    "qty_locked": false,
    "naver_price": 0,
    "manual_options": [],
    "lead_time": 10,
    "single_mode": false,
    "single_selected_imgs": [],
    "margin_override": 0.0,
    "watch_store": "제니스 트레이딩",
    "price_extra": 0,
    "extra_detail_images": [],
    "extra_detail_text": "",
    "status": "pending"
  },
  {
    "uid": "1dfaf828",
    "url": "https://smartstore.naver.com/euromarkt/products/11385968478",
    "brand": "",
    "qtys": [
      3,
      5,
      8,
      10,
      12,
      15
    ],
    "min_qty": 3,
    "volume": 0.0,
    "volume_unit": "L",
    "use_nobg": false,
    "draft": false,
    "gtin": "",
    "source_file": "하리보.txt",
    "gosisi_cat": "기타 재화",
    "category_id": "",
    "category_is_manual": false,
    "qty_locked": false,
    "naver_price": 0,
    "manual_options": [],
    "lead_time": 10,
    "single_mode": false,
    "single_selected_imgs": [],
    "margin_override": 0.0,
    "watch_store": "제니스 트레이딩",
    "price_extra": 0,
    "extra_detail_images": [],
    "extra_detail_text": "",
    "status": "pending"
  },
  {
    "uid": "3695e4fb",
    "url": "https://smartstore.naver.com/euromarkt/products/8670487672",
    "brand": "",
    "qtys": [
      3,
      5,
      8,
      10,
      12,
      15
    ],
    "min_qty": 3,
    "volume": 0.0,
    "volume_unit": "L",
    "use_nobg": false,
    "draft": false,
    "gtin": "",
    "source_file": "하리보.txt",
    "gosisi_cat": "기타 재화",
    "category_id": "",
    "category_is_manual": false,
    "qty_locked": false,
    "naver_price": 0,
    "manual_options": [],
    "lead_time": 10,
    "single_mode": false,
    "single_selected_imgs": [],
    "margin_override": 0.0,
    "watch_store": "제니스 트레이딩",
    "price_extra": 0,
    "extra_detail_images": [],
    "extra_detail_text": "",
    "status": "pending"
  },
  {
    "uid": "900b45de",
    "url": "https://smartstore.naver.com/euromarkt/products/13029962831",
    "brand": "",
    "qtys": [
      3,
      5,
      8,
      10,
      12,
      15
    ],
    "min_qty": 3,
    "volume": 0.0,
    "volume_unit": "L",
    "use_nobg": false,
    "draft": false,
    "gtin": "",
    "source_file": "하리보.txt",
    "gosisi_cat": "기타 재화",
    "category_id": "",
    "category_is_manual": false,
    "qty_locked": false,
    "naver_price": 0,
    "manual_options": [],
    "lead_time": 10,
    "single_mode": false,
    "single_selected_imgs": [],
    "margin_override": 0.0,
    "watch_store": "제니스 트레이딩",
    "price_extra": 0,
    "extra_detail_images": [],
    "extra_detail_text": "",
    "status": "pending"
  },
  {
    "uid": "4f958868",
    "url": "https://smartstore.naver.com/euromarkt/products/13025972395",
    "brand": "",
    "qtys": [
      3,
      5,
      8,
      10,
      12,
      15
    ],
    "min_qty": 3,
    "volume": 0.0,
    "volume_unit": "L",
    "use_nobg": false,
    "draft": false,
    "gtin": "",
    "source_file": "하리보.txt",
    "gosisi_cat": "기타 재화",
    "category_id": "",
    "category_is_manual": false,
    "qty_locked": false,
    "naver_price": 0,
    "manual_options": [],
    "lead_time": 10,
    "single_mode": false,
    "single_selected_imgs": [],
    "margin_override": 0.0,
    "watch_store": "제니스 트레이딩",
    "price_extra": 0,
    "extra_detail_images": [],
    "extra_detail_text": "",
    "status": "pending"
  },
  {
    "uid": "bdd79cd3",
    "url": "https://smartstore.naver.com/euromarkt/products/11815001358",
    "brand": "",
    "qtys": [
      3,
      5,
      8,
      10,
      12,
      15
    ],
    "min_qty": 3,
    "volume": 0.0,
    "volume_unit": "L",
    "use_nobg": false,
    "draft": false,
    "gtin": "",
    "source_file": "하리보.txt",
    "gosisi_cat": "기타 재화",
    "category_id": "",
    "category_is_manual": false,
    "qty_locked": false,
    "naver_price": 0,
    "manual_options": [],
    "lead_time": 10,
    "single_mode": false,
    "single_selected_imgs": [],
    "margin_override": 0.0,
    "watch_store": "제니스 트레이딩",
    "price_extra": 0,
    "extra_detail_images": [],
    "extra_detail_text": "",
    "status": "pending"
  },
  {
    "uid": "d78f4298",
    "url": "https://smartstore.naver.com/euromarkt/products/11462899416",
    "brand": "",
    "qtys": [
      3,
      5,
      8,
      10,
      12,
      15
    ],
    "min_qty": 3,
    "volume": 0.0,
    "volume_unit": "L",
    "use_nobg": false,
    "draft": false,
    "gtin": "",
    "source_file": "하리보.txt",
    "gosisi_cat": "기타 재화",
    "category_id": "",
    "category_is_manual": false,
    "qty_locked": false,
    "naver_price": 0,
    "manual_options": [],
    "lead_time": 10,
    "single_mode": false,
    "single_selected_imgs": [],
    "margin_override": 0.0,
    "watch_store": "제니스 트레이딩",
    "price_extra": 0,
    "extra_detail_images": [],
    "extra_detail_text": "",
    "status": "pending"
  },
  {
    "uid": "3d95be24",
    "url": "https://smartstore.naver.com/euromarkt/products/11462899245",
    "brand": "",
    "qtys": [
      3,
      5,
      8,
      10,
      12,
      15
    ],
    "min_qty": 3,
    "volume": 0.0,
    "volume_unit": "L",
    "use_nobg": false,
    "draft": false,
    "gtin": "",
    "source_file": "하리보.txt",
    "gosisi_cat": "기타 재화",
    "category_id": "",
    "category_is_manual": false,
    "qty_locked": false,
    "naver_price": 0,
    "manual_options": [],
    "lead_time": 10,
    "single_mode": false,
    "single_selected_imgs": [],
    "margin_override": 0.0,
    "watch_store": "제니스 트레이딩",
    "price_extra": 0,
    "extra_detail_images": [],
    "extra_detail_text": "",
    "status": "pending"
  },
  {
    "uid": "8477e446",
    "url": "https://smartstore.naver.com/euromarkt/products/11385968370",
    "brand": "",
    "qtys": [
      3,
      5,
      8,
      10,
      12,
      15
    ],
    "min_qty": 3,
    "volume": 0.0,
    "volume_unit": "L",
    "use_nobg": false,
    "draft": false,
    "gtin": "",
    "source_file": "하리보.txt",
    "gosisi_cat": "기타 재화",
    "category_id": "",
    "category_is_manual": false,
    "qty_locked": false,
    "naver_price": 0,
    "manual_options": [],
    "lead_time": 10,
    "single_mode": false,
    "single_selected_imgs": [],
    "margin_override": 0.0,
    "watch_store": "제니스 트레이딩",
    "price_extra": 0,
    "extra_detail_images": [],
    "extra_detail_text": "",
    "status": "pending"
  },
  {
    "uid": "e0ba9558",
    "url": "https://smartstore.naver.com/euromarkt/products/11385967883",
    "brand": "",
    "qtys": [
      3,
      5,
      8,
      10,
      12,
      15
    ],
    "min_qty": 3,
    "volume": 0.0,
    "volume_unit": "L",
    "use_nobg": false,
    "draft": false,
    "gtin": "",
    "source_file": "하리보.txt",
    "gosisi_cat": "기타 재화",
    "category_id": "",
    "category_is_manual": false,
    "qty_locked": false,
    "naver_price": 0,
    "manual_options": [],
    "lead_time": 10,
    "single_mode": false,
    "single_selected_imgs": [],
    "margin_override": 0.0,
    "watch_store": "제니스 트레이딩",
    "price_extra": 0,
    "extra_detail_images": [],
    "extra_detail_text": "",
    "status": "pending"
  },
  {
    "uid": "b6eef56a",
    "url": "https://smartstore.naver.com/euromarkt/products/11002995268",
    "brand": "",
    "qtys": [
      3,
      5,
      8,
      10,
      12,
      15
    ],
    "min_qty": 3,
    "volume": 0.0,
    "volume_unit": "L",
    "use_nobg": false,
    "draft": false,
    "gtin": "",
    "source_file": "하리보.txt",
    "gosisi_cat": "기타 재화",
    "category_id": "",
    "category_is_manual": false,
    "qty_locked": false,
    "naver_price": 0,
    "manual_options": [],
    "lead_time": 10,
    "single_mode": false,
    "single_selected_imgs": [],
    "margin_override": 0.0,
    "watch_store": "제니스 트레이딩",
    "price_extra": 0,
    "extra_detail_images": [],
    "extra_detail_text": "",
    "status": "pending"
  },
  {
    "uid": "18a8f4fa",
    "url": "https://smartstore.naver.com/euromarkt/products/10972096925",
    "brand": "",
    "qtys": [
      3,
      5,
      8,
      10,
      12,
      15
    ],
    "min_qty": 3,
    "volume": 0.0,
    "volume_unit": "L",
    "use_nobg": false,
    "draft": false,
    "gtin": "",
    "source_file": "하리보.txt",
    "gosisi_cat": "기타 재화",
    "category_id": "",
    "category_is_manual": false,
    "qty_locked": false,
    "naver_price": 0,
    "manual_options": [],
    "lead_time": 10,
    "single_mode": false,
    "single_selected_imgs": [],
    "margin_override": 0.0,
    "watch_store": "제니스 트레이딩",
    "price_extra": 0,
    "extra_detail_images": [],
    "extra_detail_text": "",
    "status": "pending"
  },
  {
    "uid": "8b7df8be",
    "url": "https://smartstore.naver.com/euromarkt/products/9474286009",
    "brand": "",
    "qtys": [
      3,
      5,
      8,
      10,
      12,
      15
    ],
    "min_qty": 3,
    "volume": 0.0,
    "volume_unit": "L",
    "use_nobg": false,
    "draft": false,
    "gtin": "",
    "source_file": "하리보1.txt",
    "gosisi_cat": "기타 재화",
    "category_id": "",
    "category_is_manual": false,
    "qty_locked": false,
    "naver_price": 0,
    "manual_options": [],
    "lead_time": 10,
    "single_mode": false,
    "single_selected_imgs": [],
    "margin_override": 0.0,
    "watch_store": "제니스 트레이딩",
    "price_extra": 0,
    "extra_detail_images": [],
    "extra_detail_text": "",
    "status": "pending"
  },
  {
    "uid": "0d7dbbf4",
    "url": "https://smartstore.naver.com/euromarkt/products/8670512517",
    "brand": "",
    "qtys": [
      3,
      5,
      8,
      10,
      12,
      15
    ],
    "min_qty": 3,
    "volume": 0.0,
    "volume_unit": "L",
    "use_nobg": false,
    "draft": false,
    "gtin": "",
    "source_file": "하리보1.txt",
    "gosisi_cat": "기타 재화",
    "category_id": "",
    "category_is_manual": false,
    "qty_locked": false,
    "naver_price": 0,
    "manual_options": [],
    "lead_time": 10,
    "single_mode": false,
    "single_selected_imgs": [],
    "margin_override": 0.0,
    "watch_store": "제니스 트레이딩",
    "price_extra": 0,
    "extra_detail_images": [],
    "extra_detail_text": "",
    "status": "pending"
  },
  {
    "uid": "b904249b",
    "url": "https://smartstore.naver.com/euromarkt/products/8670512007",
    "brand": "",
    "qtys": [
      3,
      5,
      8,
      10,
      12,
      15
    ],
    "min_qty": 3,
    "volume": 0.0,
    "volume_unit": "L",
    "use_nobg": false,
    "draft": false,
    "gtin": "",
    "source_file": "하리보1.txt",
    "gosisi_cat": "기타 재화",
    "category_id": "",
    "category_is_manual": false,
    "qty_locked": false,
    "naver_price": 0,
    "manual_options": [],
    "lead_time": 10,
    "single_mode": false,
    "single_selected_imgs": [],
    "margin_override": 0.0,
    "watch_store": "제니스 트레이딩",
    "price_extra": 0,
    "extra_detail_images": [],
    "extra_detail_text": "",
    "status": "pending"
  },
  {
    "uid": "57161d41",
    "url": "https://smartstore.naver.com/euromarkt/products/8670505337",
    "brand": "",
    "qtys": [
      3,
      5,
      8,
      10,
      12,
      15
    ],
    "min_qty": 3,
    "volume": 0.0,
    "volume_unit": "L",
    "use_nobg": false,
    "draft": false,
    "gtin": "",
    "source_file": "하리보1.txt",
    "gosisi_cat": "기타 재화",
    "category_id": "",
    "category_is_manual": false,
    "qty_locked": false,
    "naver_price": 0,
    "manual_options": [],
    "lead_time": 10,
    "single_mode": false,
    "single_selected_imgs": [],
    "margin_override": 0.0,
    "watch_store": "제니스 트레이딩",
    "price_extra": 0,
    "extra_detail_images": [],
    "extra_detail_text": "",
    "status": "pending"
  },
  {
    "uid": "4d1f818f",
    "url": "https://smartstore.naver.com/euromarkt/products/8670503012",
    "brand": "",
    "qtys": [
      3,
      5,
      8,
      10,
      12,
      15
    ],
    "min_qty": 3,
    "volume": 0.0,
    "volume_unit": "L",
    "use_nobg": false,
    "draft": false,
    "gtin": "",
    "source_file": "하리보1.txt",
    "gosisi_cat": "기타 재화",
    "category_id": "",
    "category_is_manual": false,
    "qty_locked": false,
    "naver_price": 0,
    "manual_options": [],
    "lead_time": 10,
    "single_mode": false,
    "single_selected_imgs": [],
    "margin_override": 0.0,
    "watch_store": "제니스 트레이딩",
    "price_extra": 0,
    "extra_detail_images": [],
    "extra_detail_text": "",
    "status": "pending"
  },
  {
    "uid": "537c35e3",
    "url": "https://smartstore.naver.com/euromarkt/products/8670492415",
    "brand": "",
    "qtys": [
      3,
      5,
      8,
      10,
      12,
      15
    ],
    "min_qty": 3,
    "volume": 0.0,
    "volume_unit": "L",
    "use_nobg": false,
    "draft": false,
    "gtin": "",
    "source_file": "하리보1.txt",
    "gosisi_cat": "기타 재화",
    "category_id": "",
    "category_is_manual": false,
    "qty_locked": false,
    "naver_price": 0,
    "manual_options": [],
    "lead_time": 10,
    "single_mode": false,
    "single_selected_imgs": [],
    "margin_override": 0.0,
    "watch_store": "제니스 트레이딩",
    "price_extra": 0,
    "extra_detail_images": [],
    "extra_detail_text": "",
    "status": "pending"
  },
  {
    "uid": "1c467931",
    "url": "https://smartstore.naver.com/euromarkt/products/8670486589",
    "brand": "",
    "qtys": [
      3,
      5,
      8,
      10,
      12,
      15
    ],
    "min_qty": 3,
    "volume": 0.0,
    "volume_unit": "L",
    "use_nobg": false,
    "draft": false,
    "gtin": "",
    "source_file": "하리보1.txt",
    "gosisi_cat": "기타 재화",
    "category_id": "",
    "category_is_manual": false,
    "qty_locked": false,
    "naver_price": 0,
    "manual_options": [],
    "lead_time": 10,
    "single_mode": false,
    "single_selected_imgs": [],
    "margin_override": 0.0,
    "watch_store": "제니스 트레이딩",
    "price_extra": 0,
    "extra_detail_images": [],
    "extra_detail_text": "",
    "status": "pending"
  },
  {
    "uid": "80a498e8",
    "url": "https://smartstore.naver.com/euromarkt/products/8670486073",
    "brand": "",
    "qtys": [
      3,
      5,
      8,
      10,
      12,
      15
    ],
    "min_qty": 3,
    "volume": 0.0,
    "volume_unit": "L",
    "use_nobg": false,
    "draft": false,
    "gtin": "",
    "source_file": "하리보1.txt",
    "gosisi_cat": "기타 재화",
    "category_id": "",
    "category_is_manual": false,
    "qty_locked": false,
    "naver_price": 0,
    "manual_options": [],
    "lead_time": 10,
    "single_mode": false,
    "single_selected_imgs": [],
    "margin_override": 0.0,
    "watch_store": "제니스 트레이딩",
    "price_extra": 0,
    "extra_detail_images": [],
    "extra_detail_text": "",
    "status": "pending"
  },
  {
    "uid": "4ea612ab",
    "url": "https://smartstore.naver.com/euromarkt/products/8670485547",
    "brand": "",
    "qtys": [
      3,
      5,
      8,
      10,
      12,
      15
    ],
    "min_qty": 3,
    "volume": 0.0,
    "volume_unit": "L",
    "use_nobg": false,
    "draft": false,
    "gtin": "",
    "source_file": "하리보1.txt",
    "gosisi_cat": "기타 재화",
    "category_id": "",
    "category_is_manual": false,
    "qty_locked": false,
    "naver_price": 0,
    "manual_options": [],
    "lead_time": 10,
    "single_mode": false,
    "single_selected_imgs": [],
    "margin_override": 0.0,
    "watch_store": "제니스 트레이딩",
    "price_extra": 0,
    "extra_detail_images": [],
    "extra_detail_text": "",
    "status": "pending"
  },
  {
    "uid": "538576f3",
    "url": "https://smartstore.naver.com/euromarkt/products/13302186630",
    "brand": "",
    "qtys": [
      3,
      5,
      8,
      10,
      12,
      15
    ],
    "min_qty": 3,
    "volume": 0.0,
    "volume_unit": "L",
    "use_nobg": false,
    "draft": false,
    "gtin": "",
    "source_file": "하리보1.txt",
    "gosisi_cat": "기타 재화",
    "category_id": "",
    "category_is_manual": false,
    "qty_locked": false,
    "naver_price": 0,
    "manual_options": [],
    "lead_time": 10,
    "single_mode": false,
    "single_selected_imgs": [],
    "margin_override": 0.0,
    "watch_store": "제니스 트레이딩",
    "price_extra": 0,
    "extra_detail_images": [],
    "extra_detail_text": "",
    "status": "pending"
  },
  {
    "uid": "9e14de6a",
    "url": "https://smartstore.naver.com/euromarkt/products/12628317368",
    "brand": "",
    "qtys": [
      3,
      5,
      8,
      10,
      12,
      15
    ],
    "min_qty": 3,
    "volume": 0.0,
    "volume_unit": "L",
    "use_nobg": false,
    "draft": false,
    "gtin": "",
    "source_file": "하리보1.txt",
    "gosisi_cat": "기타 재화",
    "category_id": "",
    "category_is_manual": false,
    "qty_locked": false,
    "naver_price": 0,
    "manual_options": [],
    "lead_time": 10,
    "single_mode": false,
    "single_selected_imgs": [],
    "margin_override": 0.0,
    "watch_store": "제니스 트레이딩",
    "price_extra": 0,
    "extra_detail_images": [],
    "extra_detail_text": "",
    "status": "pending"
  },
  {
    "uid": "488d84c1",
    "url": "https://smartstore.naver.com/euromarkt/products/12286434458",
    "brand": "",
    "qtys": [
      3,
      5,
      8,
      10,
      12,
      15
    ],
    "min_qty": 3,
    "volume": 0.0,
    "volume_unit": "L",
    "use_nobg": false,
    "draft": false,
    "gtin": "",
    "source_file": "하리보1.txt",
    "gosisi_cat": "기타 재화",
    "category_id": "",
    "category_is_manual": false,
    "qty_locked": false,
    "naver_price": 0,
    "manual_options": [],
    "lead_time": 10,
    "single_mode": false,
    "single_selected_imgs": [],
    "margin_override": 0.0,
    "watch_store": "제니스 트레이딩",
    "price_extra": 0,
    "extra_detail_images": [],
    "extra_detail_text": "",
    "status": "pending"
  },
  {
    "uid": "031bba08",
    "url": "https://smartstore.naver.com/euromarkt/products/11814997947",
    "brand": "",
    "qtys": [
      3,
      5,
      8,
      10,
      12,
      15
    ],
    "min_qty": 3,
    "volume": 0.0,
    "volume_unit": "L",
    "use_nobg": false,
    "draft": false,
    "gtin": "",
    "source_file": "하리보1.txt",
    "gosisi_cat": "기타 재화",
    "category_id": "",
    "category_is_manual": false,
    "qty_locked": false,
    "naver_price": 0,
    "manual_options": [],
    "lead_time": 10,
    "single_mode": false,
    "single_selected_imgs": [],
    "margin_override": 0.0,
    "watch_store": "제니스 트레이딩",
    "price_extra": 0,
    "extra_detail_images": [],
    "extra_detail_text": "",
    "status": "pending"
  },
  {
    "uid": "7b2140f6",
    "url": "https://smartstore.naver.com/euromarkt/products/11462899074",
    "brand": "",
    "qtys": [
      3,
      5,
      8,
      10,
      12,
      15
    ],
    "min_qty": 3,
    "volume": 0.0,
    "volume_unit": "L",
    "use_nobg": false,
    "draft": false,
    "gtin": "",
    "source_file": "하리보1.txt",
    "gosisi_cat": "기타 재화",
    "category_id": "",
    "category_is_manual": false,
    "qty_locked": false,
    "naver_price": 0,
    "manual_options": [],
    "lead_time": 10,
    "single_mode": false,
    "single_selected_imgs": [],
    "margin_override": 0.0,
    "watch_store": "제니스 트레이딩",
    "price_extra": 0,
    "extra_detail_images": [],
    "extra_detail_text": "",
    "status": "pending"
  },
  {
    "uid": "6ef9728c",
    "url": "https://smartstore.naver.com/euromarkt/products/11355465051",
    "brand": "",
    "qtys": [
      3,
      5,
      8,
      10,
      12,
      15
    ],
    "min_qty": 3,
    "volume": 0.0,
    "volume_unit": "L",
    "use_nobg": false,
    "draft": false,
    "gtin": "",
    "source_file": "하리보1.txt",
    "gosisi_cat": "기타 재화",
    "category_id": "",
    "category_is_manual": false,
    "qty_locked": false,
    "naver_price": 0,
    "manual_options": [],
    "lead_time": 10,
    "single_mode": false,
    "single_selected_imgs": [],
    "margin_override": 0.0,
    "watch_store": "제니스 트레이딩",
    "price_extra": 0,
    "extra_detail_images": [],
    "extra_detail_text": "",
    "status": "pending"
  },
  {
    "uid": "21a0b8ae",
    "url": "https://smartstore.naver.com/euromarkt/products/11355462637",
    "brand": "",
    "qtys": [
      3,
      5,
      8,
      10,
      12,
      15
    ],
    "min_qty": 3,
    "volume": 0.0,
    "volume_unit": "L",
    "use_nobg": false,
    "draft": false,
    "gtin": "",
    "source_file": "하리보1.txt",
    "gosisi_cat": "기타 재화",
    "category_id": "",
    "category_is_manual": false,
    "qty_locked": false,
    "naver_price": 0,
    "manual_options": [],
    "lead_time": 10,
    "single_mode": false,
    "single_selected_imgs": [],
    "margin_override": 0.0,
    "watch_store": "제니스 트레이딩",
    "price_extra": 0,
    "extra_detail_images": [],
    "extra_detail_text": "",
    "status": "pending"
  },
  {
    "uid": "c33a25c6",
    "url": "https://smartstore.naver.com/euromarkt/products/11116580562",
    "brand": "",
    "qtys": [
      3,
      5,
      8,
      10,
      12,
      15
    ],
    "min_qty": 3,
    "volume": 0.0,
    "volume_unit": "L",
    "use_nobg": false,
    "draft": false,
    "gtin": "",
    "source_file": "하리보1.txt",
    "gosisi_cat": "기타 재화",
    "category_id": "",
    "category_is_manual": false,
    "qty_locked": false,
    "naver_price": 0,
    "manual_options": [],
    "lead_time": 10,
    "single_mode": false,
    "single_selected_imgs": [],
    "margin_override": 0.0,
    "watch_store": "제니스 트레이딩",
    "price_extra": 0,
    "extra_detail_images": [],
    "extra_detail_text": "",
    "status": "pending"
  },
  {
    "uid": "73e98187",
    "url": "https://smartstore.naver.com/euromarkt/products/11116580259",
    "brand": "",
    "qtys": [
      3,
      5,
      8,
      10,
      12,
      15
    ],
    "min_qty": 3,
    "volume": 0.0,
    "volume_unit": "L",
    "use_nobg": false,
    "draft": false,
    "gtin": "",
    "source_file": "하리보1.txt",
    "gosisi_cat": "기타 재화",
    "category_id": "",
    "category_is_manual": false,
    "qty_locked": false,
    "naver_price": 0,
    "manual_options": [],
    "lead_time": 10,
    "single_mode": false,
    "single_selected_imgs": [],
    "margin_override": 0.0,
    "watch_store": "제니스 트레이딩",
    "price_extra": 0,
    "extra_detail_images": [],
    "extra_detail_text": "",
    "status": "pending"
  },
  {
    "uid": "8cffbd08",
    "url": "https://smartstore.naver.com/euromarkt/products/10972098641",
    "brand": "",
    "qtys": [
      3,
      5,
      8,
      10,
      12,
      15
    ],
    "min_qty": 3,
    "volume": 0.0,
    "volume_unit": "L",
    "use_nobg": false,
    "draft": false,
    "gtin": "",
    "source_file": "하리보1.txt",
    "gosisi_cat": "기타 재화",
    "category_id": "",
    "category_is_manual": false,
    "qty_locked": false,
    "naver_price": 0,
    "manual_options": [],
    "lead_time": 10,
    "single_mode": false,
    "single_selected_imgs": [],
    "margin_override": 0.0,
    "watch_store": "제니스 트레이딩",
    "price_extra": 0,
    "extra_detail_images": [],
    "extra_detail_text": "",
    "status": "pending"
  },
  {
    "uid": "178ec91b",
    "url": "https://smartstore.naver.com/euromarkt/products/10972098077",
    "brand": "",
    "qtys": [
      3,
      5,
      8,
      10,
      12,
      15
    ],
    "min_qty": 3,
    "volume": 0.0,
    "volume_unit": "L",
    "use_nobg": false,
    "draft": false,
    "gtin": "",
    "source_file": "하리보1.txt",
    "gosisi_cat": "기타 재화",
    "category_id": "",
    "category_is_manual": false,
    "qty_locked": false,
    "naver_price": 0,
    "manual_options": [],
    "lead_time": 10,
    "single_mode": false,
    "single_selected_imgs": [],
    "margin_override": 0.0,
    "watch_store": "제니스 트레이딩",
    "price_extra": 0,
    "extra_detail_images": [],
    "extra_detail_text": "",
    "status": "pending"
  },
  {
    "uid": "02c53810",
    "url": "https://smartstore.naver.com/euromarkt/products/10972097288",
    "brand": "",
    "qtys": [
      3,
      5,
      8,
      10,
      12,
      15
    ],
    "min_qty": 3,
    "volume": 0.0,
    "volume_unit": "L",
    "use_nobg": false,
    "draft": false,
    "gtin": "",
    "source_file": "하리보1.txt",
    "gosisi_cat": "기타 재화",
    "category_id": "",
    "category_is_manual": false,
    "qty_locked": false,
    "naver_price": 0,
    "manual_options": [],
    "lead_time": 10,
    "single_mode": false,
    "single_selected_imgs": [],
    "margin_override": 0.0,
    "watch_store": "제니스 트레이딩",
    "price_extra": 0,
    "extra_detail_images": [],
    "extra_detail_text": "",
    "status": "pending"
  },
  {
    "uid": "1d61e282",
    "url": "https://smartstore.naver.com/euromarkt/products/10972096711",
    "brand": "",
    "qtys": [
      3,
      5,
      8,
      10,
      12,
      15
    ],
    "min_qty": 3,
    "volume": 0.0,
    "volume_unit": "L",
    "use_nobg": false,
    "draft": false,
    "gtin": "",
    "source_file": "하리보1.txt",
    "gosisi_cat": "기타 재화",
    "category_id": "",
    "category_is_manual": false,
    "qty_locked": false,
    "naver_price": 0,
    "manual_options": [],
    "lead_time": 10,
    "single_mode": false,
    "single_selected_imgs": [],
    "margin_override": 0.0,
    "watch_store": "제니스 트레이딩",
    "price_extra": 0,
    "extra_detail_images": [],
    "extra_detail_text": "",
    "status": "pending"
  },
  {
    "uid": "d51e9b08",
    "url": "https://smartstore.naver.com/euromarkt/products/10972095493",
    "brand": "",
    "qtys": [
      3,
      5,
      8,
      10,
      12,
      15
    ],
    "min_qty": 3,
    "volume": 0.0,
    "volume_unit": "L",
    "use_nobg": false,
    "draft": false,
    "gtin": "",
    "source_file": "하리보1.txt",
    "gosisi_cat": "기타 재화",
    "category_id": "",
    "category_is_manual": false,
    "qty_locked": false,
    "naver_price": 0,
    "manual_options": [],
    "lead_time": 10,
    "single_mode": false,
    "single_selected_imgs": [],
    "margin_override": 0.0,
    "watch_store": "제니스 트레이딩",
    "price_extra": 0,
    "extra_detail_images": [],
    "extra_detail_text": "",
    "status": "pending"
  },
  {
    "uid": "be62fae1",
    "url": "https://smartstore.naver.com/euromarkt/products/9474285982",
    "brand": "",
    "qtys": [
      3,
      5,
      8,
      10,
      12,
      15
    ],
    "min_qty": 3,
    "volume": 0.0,
    "volume_unit": "L",
    "use_nobg": false,
    "draft": false,
    "gtin": "",
    "source_file": "하리보1.txt",
    "gosisi_cat": "기타 재화",
    "category_id": "",
    "category_is_manual": false,
    "qty_locked": false,
    "naver_price": 0,
    "manual_options": [],
    "lead_time": 10,
    "single_mode": false,
    "single_selected_imgs": [],
    "margin_override": 0.0,
    "watch_store": "제니스 트레이딩",
    "price_extra": 0,
    "extra_detail_images": [],
    "extra_detail_text": "",
    "status": "pending"
  },
  {
    "uid": "8e3321dd",
    "url": "https://smartstore.naver.com/euromarkt/products/8670497588",
    "brand": "",
    "qtys": [
      3,
      5,
      8,
      10,
      12,
      15
    ],
    "min_qty": 3,
    "volume": 0.0,
    "volume_unit": "L",
    "use_nobg": false,
    "draft": false,
    "gtin": "",
    "source_file": "하리보1.txt",
    "gosisi_cat": "기타 재화",
    "category_id": "",
    "category_is_manual": false,
    "qty_locked": false,
    "naver_price": 0,
    "manual_options": [],
    "lead_time": 10,
    "single_mode": false,
    "single_selected_imgs": [],
    "margin_override": 0.0,
    "watch_store": "제니스 트레이딩",
    "price_extra": 0,
    "extra_detail_images": [],
    "extra_detail_text": "",
    "status": "pending"
  },
  {
    "uid": "a87b613e",
    "url": "https://smartstore.naver.com/euromarkt/products/8670496215",
    "brand": "",
    "qtys": [
      3,
      5,
      8,
      10,
      12,
      15
    ],
    "min_qty": 3,
    "volume": 0.0,
    "volume_unit": "L",
    "use_nobg": false,
    "draft": false,
    "gtin": "",
    "source_file": "하리보1.txt",
    "gosisi_cat": "기타 재화",
    "category_id": "",
    "category_is_manual": false,
    "qty_locked": false,
    "naver_price": 0,
    "manual_options": [],
    "lead_time": 10,
    "single_mode": false,
    "single_selected_imgs": [],
    "margin_override": 0.0,
    "watch_store": "제니스 트레이딩",
    "price_extra": 0,
    "extra_detail_images": [],
    "extra_detail_text": "",
    "status": "pending"
  },
  {
    "uid": "170e694c",
    "url": "https://smartstore.naver.com/euromarkt/products/8670487130",
    "brand": "",
    "qtys": [
      3,
      5,
      8,
      10,
      12,
      15
    ],
    "min_qty": 3,
    "volume": 0.0,
    "volume_unit": "L",
    "use_nobg": false,
    "draft": false,
    "gtin": "",
    "source_file": "하리보1.txt",
    "gosisi_cat": "기타 재화",
    "category_id": "",
    "category_is_manual": false,
    "qty_locked": false,
    "naver_price": 0,
    "manual_options": [],
    "lead_time": 10,
    "single_mode": false,
    "single_selected_imgs": [],
    "margin_override": 0.0,
    "watch_store": "제니스 트레이딩",
    "price_extra": 0,
    "extra_detail_images": [],
    "extra_detail_text": "",
    "status": "pending"
  },
  {
    "uid": "420c3635",
    "url": "https://smartstore.naver.com/euromarkt/products/8670484904",
    "brand": "",
    "qtys": [
      3,
      5,
      8,
      10,
      12,
      15
    ],
    "min_qty": 3,
    "volume": 0.0,
    "volume_unit": "L",
    "use_nobg": false,
    "draft": false,
    "gtin": "",
    "source_file": "하리보1.txt",
    "gosisi_cat": "기타 재화",
    "category_id": "",
    "category_is_manual": false,
    "qty_locked": false,
    "naver_price": 0,
    "manual_options": [],
    "lead_time": 10,
    "single_mode": false,
    "single_selected_imgs": [],
    "margin_override": 0.0,
    "watch_store": "제니스 트레이딩",
    "price_extra": 0,
    "extra_detail_images": [],
    "extra_detail_text": "",
    "status": "pending"
  },
  {
    "uid": "b658562c",
    "url": "https://smartstore.naver.com/euromarkt/products/13561590273",
    "brand": "",
    "qtys": [
      3,
      5,
      8,
      10,
      12,
      15
    ],
    "min_qty": 3,
    "volume": 0.0,
    "volume_unit": "L",
    "use_nobg": false,
    "draft": false,
    "gtin": "",
    "source_file": "하리보1.txt",
    "gosisi_cat": "기타 재화",
    "category_id": "",
    "category_is_manual": false,
    "qty_locked": false,
    "naver_price": 0,
    "manual_options": [],
    "lead_time": 10,
    "single_mode": false,
    "single_selected_imgs": [],
    "margin_override": 0.0,
    "watch_store": "제니스 트레이딩",
    "price_extra": 0,
    "extra_detail_images": [],
    "extra_detail_text": "",
    "status": "pending"
  },
  {
    "uid": "eb1dcf37",
    "url": "https://smartstore.naver.com/euromarkt/products/13561590187",
    "brand": "",
    "qtys": [
      3,
      5,
      8,
      10,
      12,
      15
    ],
    "min_qty": 3,
    "volume": 0.0,
    "volume_unit": "L",
    "use_nobg": false,
    "draft": false,
    "gtin": "",
    "source_file": "하리보1.txt",
    "gosisi_cat": "기타 재화",
    "category_id": "",
    "category_is_manual": false,
    "qty_locked": false,
    "naver_price": 0,
    "manual_options": [],
    "lead_time": 10,
    "single_mode": false,
    "single_selected_imgs": [],
    "margin_override": 0.0,
    "watch_store": "제니스 트레이딩",
    "price_extra": 0,
    "extra_detail_images": [],
    "extra_detail_text": "",
    "status": "pending"
  },
  {
    "uid": "a134b426",
    "url": "https://smartstore.naver.com/euromarkt/products/13561590100",
    "brand": "",
    "qtys": [
      3,
      5,
      8,
      10,
      12,
      15
    ],
    "min_qty": 3,
    "volume": 0.0,
    "volume_unit": "L",
    "use_nobg": false,
    "draft": false,
    "gtin": "",
    "source_file": "하리보1.txt",
    "gosisi_cat": "기타 재화",
    "category_id": "",
    "category_is_manual": false,
    "qty_locked": false,
    "naver_price": 0,
    "manual_options": [],
    "lead_time": 10,
    "single_mode": false,
    "single_selected_imgs": [],
    "margin_override": 0.0,
    "watch_store": "제니스 트레이딩",
    "price_extra": 0,
    "extra_detail_images": [],
    "extra_detail_text": "",
    "status": "pending"
  },
  {
    "uid": "7d4fa96b",
    "url": "https://smartstore.naver.com/euromarkt/products/13527145889",
    "brand": "",
    "qtys": [
      3,
      5,
      8,
      10,
      12,
      15
    ],
    "min_qty": 3,
    "volume": 0.0,
    "volume_unit": "L",
    "use_nobg": false,
    "draft": false,
    "gtin": "",
    "source_file": "하리보1.txt",
    "gosisi_cat": "기타 재화",
    "category_id": "",
    "category_is_manual": false,
    "qty_locked": false,
    "naver_price": 0,
    "manual_options": [],
    "lead_time": 10,
    "single_mode": false,
    "single_selected_imgs": [],
    "margin_override": 0.0,
    "watch_store": "제니스 트레이딩",
    "price_extra": 0,
    "extra_detail_images": [],
    "extra_detail_text": "",
    "status": "pending"
  },
  {
    "uid": "b60f57c3",
    "url": "https://smartstore.naver.com/euromarkt/products/13527145333",
    "brand": "",
    "qtys": [
      3,
      5,
      8,
      10,
      12,
      15
    ],
    "min_qty": 3,
    "volume": 0.0,
    "volume_unit": "L",
    "use_nobg": false,
    "draft": false,
    "gtin": "",
    "source_file": "하리보1.txt",
    "gosisi_cat": "기타 재화",
    "category_id": "",
    "category_is_manual": false,
    "qty_locked": false,
    "naver_price": 0,
    "manual_options": [],
    "lead_time": 10,
    "single_mode": false,
    "single_selected_imgs": [],
    "margin_override": 0.0,
    "watch_store": "제니스 트레이딩",
    "price_extra": 0,
    "extra_detail_images": [],
    "extra_detail_text": "",
    "status": "pending"
  },
  {
    "uid": "d5b9bbb1",
    "url": "https://smartstore.naver.com/euromarkt/products/13302186802",
    "brand": "",
    "qtys": [
      3,
      5,
      8,
      10,
      12,
      15
    ],
    "min_qty": 3,
    "volume": 0.0,
    "volume_unit": "L",
    "use_nobg": false,
    "draft": false,
    "gtin": "",
    "source_file": "하리보1.txt",
    "gosisi_cat": "기타 재화",
    "category_id": "",
    "category_is_manual": false,
    "qty_locked": false,
    "naver_price": 0,
    "manual_options": [],
    "lead_time": 10,
    "single_mode": false,
    "single_selected_imgs": [],
    "margin_override": 0.0,
    "watch_store": "제니스 트레이딩",
    "price_extra": 0,
    "extra_detail_images": [],
    "extra_detail_text": "",
    "status": "pending"
  },
  {
    "uid": "1bf45b1c",
    "url": "https://smartstore.naver.com/euromarkt/products/13154302160",
    "brand": "",
    "qtys": [
      3,
      5,
      8,
      10,
      12,
      15
    ],
    "min_qty": 3,
    "volume": 0.0,
    "volume_unit": "L",
    "use_nobg": false,
    "draft": false,
    "gtin": "",
    "source_file": "하리보1.txt",
    "gosisi_cat": "기타 재화",
    "category_id": "",
    "category_is_manual": false,
    "qty_locked": false,
    "naver_price": 0,
    "manual_options": [],
    "lead_time": 10,
    "single_mode": false,
    "single_selected_imgs": [],
    "margin_override": 0.0,
    "watch_store": "제니스 트레이딩",
    "price_extra": 0,
    "extra_detail_images": [],
    "extra_detail_text": "",
    "status": "pending"
  },
  {
    "uid": "ca91f261",
    "url": "https://smartstore.naver.com/euromarkt/products/13154293489",
    "brand": "",
    "qtys": [
      3,
      5,
      8,
      10,
      12,
      15
    ],
    "min_qty": 3,
    "volume": 0.0,
    "volume_unit": "L",
    "use_nobg": false,
    "draft": false,
    "gtin": "",
    "source_file": "하리보1.txt",
    "gosisi_cat": "기타 재화",
    "category_id": "",
    "category_is_manual": false,
    "qty_locked": false,
    "naver_price": 0,
    "manual_options": [],
    "lead_time": 10,
    "single_mode": false,
    "single_selected_imgs": [],
    "margin_override": 0.0,
    "watch_store": "제니스 트레이딩",
    "price_extra": 0,
    "extra_detail_images": [],
    "extra_detail_text": "",
    "status": "pending"
  },
  {
    "uid": "350d01a3",
    "url": "https://smartstore.naver.com/euromarkt/products/13025970485",
    "brand": "",
    "qtys": [
      3,
      5,
      8,
      10,
      12,
      15
    ],
    "min_qty": 3,
    "volume": 0.0,
    "volume_unit": "L",
    "use_nobg": false,
    "draft": false,
    "gtin": "",
    "source_file": "하리보2.txt",
    "gosisi_cat": "기타 재화",
    "category_id": "",
    "category_is_manual": false,
    "qty_locked": false,
    "naver_price": 0,
    "manual_options": [],
    "lead_time": 10,
    "single_mode": false,
    "single_selected_imgs": [],
    "margin_override": 0.0,
    "watch_store": "제니스 트레이딩",
    "price_extra": 0,
    "extra_detail_images": [],
    "extra_detail_text": "",
    "status": "pending"
  },
  {
    "uid": "80c0f82c",
    "url": "https://smartstore.naver.com/euromarkt/products/12773574797",
    "brand": "",
    "qtys": [
      3,
      5,
      8,
      10,
      12,
      15
    ],
    "min_qty": 3,
    "volume": 0.0,
    "volume_unit": "L",
    "use_nobg": false,
    "draft": false,
    "gtin": "",
    "source_file": "하리보2.txt",
    "gosisi_cat": "기타 재화",
    "category_id": "",
    "category_is_manual": false,
    "qty_locked": false,
    "naver_price": 0,
    "manual_options": [],
    "lead_time": 10,
    "single_mode": false,
    "single_selected_imgs": [],
    "margin_override": 0.0,
    "watch_store": "제니스 트레이딩",
    "price_extra": 0,
    "extra_detail_images": [],
    "extra_detail_text": "",
    "status": "pending"
  },
  {
    "uid": "21c8697e",
    "url": "https://smartstore.naver.com/euromarkt/products/12538277383",
    "brand": "",
    "qtys": [
      3,
      5,
      8,
      10,
      12,
      15
    ],
    "min_qty": 3,
    "volume": 0.0,
    "volume_unit": "L",
    "use_nobg": false,
    "draft": false,
    "gtin": "",
    "source_file": "하리보2.txt",
    "gosisi_cat": "기타 재화",
    "category_id": "",
    "category_is_manual": false,
    "qty_locked": false,
    "naver_price": 0,
    "manual_options": [],
    "lead_time": 10,
    "single_mode": false,
    "single_selected_imgs": [],
    "margin_override": 0.0,
    "watch_store": "제니스 트레이딩",
    "price_extra": 0,
    "extra_detail_images": [],
    "extra_detail_text": "",
    "status": "pending"
  },
  {
    "uid": "f9ba1eb2",
    "url": "https://smartstore.naver.com/euromarkt/products/12538274107",
    "brand": "",
    "qtys": [
      3,
      5,
      8,
      10,
      12,
      15
    ],
    "min_qty": 3,
    "volume": 0.0,
    "volume_unit": "L",
    "use_nobg": false,
    "draft": false,
    "gtin": "",
    "source_file": "하리보2.txt",
    "gosisi_cat": "기타 재화",
    "category_id": "",
    "category_is_manual": false,
    "qty_locked": false,
    "naver_price": 0,
    "manual_options": [],
    "lead_time": 10,
    "single_mode": false,
    "single_selected_imgs": [],
    "margin_override": 0.0,
    "watch_store": "제니스 트레이딩",
    "price_extra": 0,
    "extra_detail_images": [],
    "extra_detail_text": "",
    "status": "pending"
  },
  {
    "uid": "8f71633c",
    "url": "https://smartstore.naver.com/euromarkt/products/12286434151",
    "brand": "",
    "qtys": [
      3,
      5,
      8,
      10,
      12,
      15
    ],
    "min_qty": 3,
    "volume": 0.0,
    "volume_unit": "L",
    "use_nobg": false,
    "draft": false,
    "gtin": "",
    "source_file": "하리보2.txt",
    "gosisi_cat": "기타 재화",
    "category_id": "",
    "category_is_manual": false,
    "qty_locked": false,
    "naver_price": 0,
    "manual_options": [],
    "lead_time": 10,
    "single_mode": false,
    "single_selected_imgs": [],
    "margin_override": 0.0,
    "watch_store": "제니스 트레이딩",
    "price_extra": 0,
    "extra_detail_images": [],
    "extra_detail_text": "",
    "status": "pending"
  },
  {
    "uid": "a689a63f",
    "url": "https://smartstore.naver.com/euromarkt/products/11814997887",
    "brand": "",
    "qtys": [
      3,
      5,
      8,
      10,
      12,
      15
    ],
    "min_qty": 3,
    "volume": 0.0,
    "volume_unit": "L",
    "use_nobg": false,
    "draft": false,
    "gtin": "",
    "source_file": "하리보2.txt",
    "gosisi_cat": "기타 재화",
    "category_id": "",
    "category_is_manual": false,
    "qty_locked": false,
    "naver_price": 0,
    "manual_options": [],
    "lead_time": 10,
    "single_mode": false,
    "single_selected_imgs": [],
    "margin_override": 0.0,
    "watch_store": "제니스 트레이딩",
    "price_extra": 0,
    "extra_detail_images": [],
    "extra_detail_text": "",
    "status": "pending"
  },
  {
    "uid": "09ee3c37",
    "url": "https://smartstore.naver.com/euromarkt/products/11462899329",
    "brand": "",
    "qtys": [
      3,
      5,
      8,
      10,
      12,
      15
    ],
    "min_qty": 3,
    "volume": 0.0,
    "volume_unit": "L",
    "use_nobg": false,
    "draft": false,
    "gtin": "",
    "source_file": "하리보2.txt",
    "gosisi_cat": "기타 재화",
    "category_id": "",
    "category_is_manual": false,
    "qty_locked": false,
    "naver_price": 0,
    "manual_options": [],
    "lead_time": 10,
    "single_mode": false,
    "single_selected_imgs": [],
    "margin_override": 0.0,
    "watch_store": "제니스 트레이딩",
    "price_extra": 0,
    "extra_detail_images": [],
    "extra_detail_text": "",
    "status": "pending"
  },
  {
    "uid": "43b64eef",
    "url": "https://smartstore.naver.com/euromarkt/products/11462899152",
    "brand": "",
    "qtys": [
      3,
      5,
      8,
      10,
      12,
      15
    ],
    "min_qty": 3,
    "volume": 0.0,
    "volume_unit": "L",
    "use_nobg": false,
    "draft": false,
    "gtin": "",
    "source_file": "하리보2.txt",
    "gosisi_cat": "기타 재화",
    "category_id": "",
    "category_is_manual": false,
    "qty_locked": false,
    "naver_price": 0,
    "manual_options": [],
    "lead_time": 10,
    "single_mode": false,
    "single_selected_imgs": [],
    "margin_override": 0.0,
    "watch_store": "제니스 트레이딩",
    "price_extra": 0,
    "extra_detail_images": [],
    "extra_detail_text": "",
    "status": "pending"
  },
  {
    "uid": "52bdd5ef",
    "url": "https://smartstore.naver.com/euromarkt/products/11385968953",
    "brand": "",
    "qtys": [
      3,
      5,
      8,
      10,
      12,
      15
    ],
    "min_qty": 3,
    "volume": 0.0,
    "volume_unit": "L",
    "use_nobg": false,
    "draft": false,
    "gtin": "",
    "source_file": "하리보2.txt",
    "gosisi_cat": "기타 재화",
    "category_id": "",
    "category_is_manual": false,
    "qty_locked": false,
    "naver_price": 0,
    "manual_options": [],
    "lead_time": 10,
    "single_mode": false,
    "single_selected_imgs": [],
    "margin_override": 0.0,
    "watch_store": "제니스 트레이딩",
    "price_extra": 0,
    "extra_detail_images": [],
    "extra_detail_text": "",
    "status": "pending"
  },
  {
    "uid": "64db3a4e",
    "url": "https://smartstore.naver.com/euromarkt/products/11385968075",
    "brand": "",
    "qtys": [
      3,
      5,
      8,
      10,
      12,
      15
    ],
    "min_qty": 3,
    "volume": 0.0,
    "volume_unit": "L",
    "use_nobg": false,
    "draft": false,
    "gtin": "",
    "source_file": "하리보2.txt",
    "gosisi_cat": "기타 재화",
    "category_id": "",
    "category_is_manual": false,
    "qty_locked": false,
    "naver_price": 0,
    "manual_options": [],
    "lead_time": 10,
    "single_mode": false,
    "single_selected_imgs": [],
    "margin_override": 0.0,
    "watch_store": "제니스 트레이딩",
    "price_extra": 0,
    "extra_detail_images": [],
    "extra_detail_text": "",
    "status": "pending"
  },
  {
    "uid": "00e7a1f8",
    "url": "https://smartstore.naver.com/euromarkt/products/11355464943",
    "brand": "",
    "qtys": [
      3,
      5,
      8,
      10,
      12,
      15
    ],
    "min_qty": 3,
    "volume": 0.0,
    "volume_unit": "L",
    "use_nobg": false,
    "draft": false,
    "gtin": "",
    "source_file": "하리보2.txt",
    "gosisi_cat": "기타 재화",
    "category_id": "",
    "category_is_manual": false,
    "qty_locked": false,
    "naver_price": 0,
    "manual_options": [],
    "lead_time": 10,
    "single_mode": false,
    "single_selected_imgs": [],
    "margin_override": 0.0,
    "watch_store": "제니스 트레이딩",
    "price_extra": 0,
    "extra_detail_images": [],
    "extra_detail_text": "",
    "status": "pending"
  },
  {
    "uid": "f67a79b6",
    "url": "https://smartstore.naver.com/euromarkt/products/11355462888",
    "brand": "",
    "qtys": [
      3,
      5,
      8,
      10,
      12,
      15
    ],
    "min_qty": 3,
    "volume": 0.0,
    "volume_unit": "L",
    "use_nobg": false,
    "draft": false,
    "gtin": "",
    "source_file": "하리보2.txt",
    "gosisi_cat": "기타 재화",
    "category_id": "",
    "category_is_manual": false,
    "qty_locked": false,
    "naver_price": 0,
    "manual_options": [],
    "lead_time": 10,
    "single_mode": false,
    "single_selected_imgs": [],
    "margin_override": 0.0,
    "watch_store": "제니스 트레이딩",
    "price_extra": 0,
    "extra_detail_images": [],
    "extra_detail_text": "",
    "status": "pending"
  },
  {
    "uid": "40b83a48",
    "url": "https://smartstore.naver.com/euromarkt/products/11355462765\\",
    "brand": "",
    "qtys": [
      3,
      5,
      8,
      10,
      12,
      15
    ],
    "min_qty": 3,
    "volume": 0.0,
    "volume_unit": "L",
    "use_nobg": false,
    "draft": false,
    "gtin": "",
    "source_file": "하리보2.txt",
    "gosisi_cat": "기타 재화",
    "category_id": "",
    "category_is_manual": false,
    "qty_locked": false,
    "naver_price": 0,
    "manual_options": [],
    "lead_time": 10,
    "single_mode": false,
    "single_selected_imgs": [],
    "margin_override": 0.0,
    "watch_store": "제니스 트레이딩",
    "price_extra": 0,
    "extra_detail_images": [],
    "extra_detail_text": "",
    "status": "pending"
  },
  {
    "uid": "4eb97e1a",
    "url": "https://smartstore.naver.com/euromarkt/products/11355461991",
    "brand": "",
    "qtys": [
      3,
      5,
      8,
      10,
      12,
      15
    ],
    "min_qty": 3,
    "volume": 0.0,
    "volume_unit": "L",
    "use_nobg": false,
    "draft": false,
    "gtin": "",
    "source_file": "하리보3.txt",
    "gosisi_cat": "기타 재화",
    "category_id": "",
    "category_is_manual": false,
    "qty_locked": false,
    "naver_price": 0,
    "manual_options": [],
    "lead_time": 10,
    "single_mode": false,
    "single_selected_imgs": [],
    "margin_override": 0.0,
    "watch_store": "제니스 트레이딩",
    "price_extra": 0,
    "extra_detail_images": [],
    "extra_detail_text": "",
    "status": "pending"
  },
  {
    "uid": "a96f2ae3",
    "url": "https://smartstore.naver.com/euromarkt/products/11252988215",
    "brand": "",
    "qtys": [
      3,
      5,
      8,
      10,
      12,
      15
    ],
    "min_qty": 3,
    "volume": 0.0,
    "volume_unit": "L",
    "use_nobg": false,
    "draft": false,
    "gtin": "",
    "source_file": "하리보3.txt",
    "gosisi_cat": "기타 재화",
    "category_id": "",
    "category_is_manual": false,
    "qty_locked": false,
    "naver_price": 0,
    "manual_options": [],
    "lead_time": 10,
    "single_mode": false,
    "single_selected_imgs": [],
    "margin_override": 0.0,
    "watch_store": "제니스 트레이딩",
    "price_extra": 0,
    "extra_detail_images": [],
    "extra_detail_text": "",
    "status": "pending"
  },
  {
    "uid": "7aa5f850",
    "url": "https://smartstore.naver.com/euromarkt/products/11252987852",
    "brand": "",
    "qtys": [
      3,
      5,
      8,
      10,
      12,
      15
    ],
    "min_qty": 3,
    "volume": 0.0,
    "volume_unit": "L",
    "use_nobg": false,
    "draft": false,
    "gtin": "",
    "source_file": "하리보3.txt",
    "gosisi_cat": "기타 재화",
    "category_id": "",
    "category_is_manual": false,
    "qty_locked": false,
    "naver_price": 0,
    "manual_options": [],
    "lead_time": 10,
    "single_mode": false,
    "single_selected_imgs": [],
    "margin_override": 0.0,
    "watch_store": "제니스 트레이딩",
    "price_extra": 0,
    "extra_detail_images": [],
    "extra_detail_text": "",
    "status": "pending"
  },
  {
    "uid": "2e0549de",
    "url": "https://smartstore.naver.com/euromarkt/products/11116580431",
    "brand": "",
    "qtys": [
      3,
      5,
      8,
      10,
      12,
      15
    ],
    "min_qty": 3,
    "volume": 0.0,
    "volume_unit": "L",
    "use_nobg": false,
    "draft": false,
    "gtin": "",
    "source_file": "하리보3.txt",
    "gosisi_cat": "기타 재화",
    "category_id": "",
    "category_is_manual": false,
    "qty_locked": false,
    "naver_price": 0,
    "manual_options": [],
    "lead_time": 10,
    "single_mode": false,
    "single_selected_imgs": [],
    "margin_override": 0.0,
    "watch_store": "제니스 트레이딩",
    "price_extra": 0,
    "extra_detail_images": [],
    "extra_detail_text": "",
    "status": "pending"
  },
  {
    "uid": "9d09579b",
    "url": "https://smartstore.naver.com/euromarkt/products/11116580139",
    "brand": "",
    "qtys": [
      3,
      5,
      8,
      10,
      12,
      15
    ],
    "min_qty": 3,
    "volume": 0.0,
    "volume_unit": "L",
    "use_nobg": false,
    "draft": false,
    "gtin": "",
    "source_file": "하리보3.txt",
    "gosisi_cat": "기타 재화",
    "category_id": "",
    "category_is_manual": false,
    "qty_locked": false,
    "naver_price": 0,
    "manual_options": [],
    "lead_time": 10,
    "single_mode": false,
    "single_selected_imgs": [],
    "margin_override": 0.0,
    "watch_store": "제니스 트레이딩",
    "price_extra": 0,
    "extra_detail_images": [],
    "extra_detail_text": "",
    "status": "pending"
  },
  {
    "uid": "c67f9601",
    "url": "https://smartstore.naver.com/euromarkt/products/11116579867",
    "brand": "",
    "qtys": [
      3,
      5,
      8,
      10,
      12,
      15
    ],
    "min_qty": 3,
    "volume": 0.0,
    "volume_unit": "L",
    "use_nobg": false,
    "draft": false,
    "gtin": "",
    "source_file": "하리보3.txt",
    "gosisi_cat": "기타 재화",
    "category_id": "",
    "category_is_manual": false,
    "qty_locked": false,
    "naver_price": 0,
    "manual_options": [],
    "lead_time": 10,
    "single_mode": false,
    "single_selected_imgs": [],
    "margin_override": 0.0,
    "watch_store": "제니스 트레이딩",
    "price_extra": 0,
    "extra_detail_images": [],
    "extra_detail_text": "",
    "status": "pending"
  },
  {
    "uid": "6bffa0b1",
    "url": "https://smartstore.naver.com/euromarkt/products/11002995108",
    "brand": "",
    "qtys": [
      3,
      5,
      8,
      10,
      12,
      15
    ],
    "min_qty": 3,
    "volume": 0.0,
    "volume_unit": "L",
    "use_nobg": false,
    "draft": false,
    "gtin": "",
    "source_file": "하리보3.txt",
    "gosisi_cat": "기타 재화",
    "category_id": "",
    "category_is_manual": false,
    "qty_locked": false,
    "naver_price": 0,
    "manual_options": [],
    "lead_time": 10,
    "single_mode": false,
    "single_selected_imgs": [],
    "margin_override": 0.0,
    "watch_store": "제니스 트레이딩",
    "price_extra": 0,
    "extra_detail_images": [],
    "extra_detail_text": "",
    "status": "pending"
  },
  {
    "uid": "d2bad256",
    "url": "https://smartstore.naver.com/euromarkt/products/10972097893",
    "brand": "",
    "qtys": [
      3,
      5,
      8,
      10,
      12,
      15
    ],
    "min_qty": 3,
    "volume": 0.0,
    "volume_unit": "L",
    "use_nobg": false,
    "draft": false,
    "gtin": "",
    "source_file": "하리보3.txt",
    "gosisi_cat": "기타 재화",
    "category_id": "",
    "category_is_manual": false,
    "qty_locked": false,
    "naver_price": 0,
    "manual_options": [],
    "lead_time": 10,
    "single_mode": false,
    "single_selected_imgs": [],
    "margin_override": 0.0,
    "watch_store": "제니스 트레이딩",
    "price_extra": 0,
    "extra_detail_images": [],
    "extra_detail_text": "",
    "status": "pending"
  },
  {
    "uid": "06f745f1",
    "url": "https://smartstore.naver.com/euromarkt/products/10972097207",
    "brand": "",
    "qtys": [
      3,
      5,
      8,
      10,
      12,
      15
    ],
    "min_qty": 3,
    "volume": 0.0,
    "volume_unit": "L",
    "use_nobg": false,
    "draft": false,
    "gtin": "",
    "source_file": "하리보3.txt",
    "gosisi_cat": "기타 재화",
    "category_id": "",
    "category_is_manual": false,
    "qty_locked": false,
    "naver_price": 0,
    "manual_options": [],
    "lead_time": 10,
    "single_mode": false,
    "single_selected_imgs": [],
    "margin_override": 0.0,
    "watch_store": "제니스 트레이딩",
    "price_extra": 0,
    "extra_detail_images": [],
    "extra_detail_text": "",
    "status": "pending"
  },
  {
    "uid": "dd8bccc4",
    "url": "https://smartstore.naver.com/euromarkt/products/10972096835",
    "brand": "",
    "qtys": [
      3,
      5,
      8,
      10,
      12,
      15
    ],
    "min_qty": 3,
    "volume": 0.0,
    "volume_unit": "L",
    "use_nobg": false,
    "draft": false,
    "gtin": "",
    "source_file": "하리보3.txt",
    "gosisi_cat": "기타 재화",
    "category_id": "",
    "category_is_manual": false,
    "qty_locked": false,
    "naver_price": 0,
    "manual_options": [],
    "lead_time": 10,
    "single_mode": false,
    "single_selected_imgs": [],
    "margin_override": 0.0,
    "watch_store": "제니스 트레이딩",
    "price_extra": 0,
    "extra_detail_images": [],
    "extra_detail_text": "",
    "status": "pending"
  },
  {
    "uid": "eed60ec8",
    "url": "https://smartstore.naver.com/euromarkt/products/10972095581",
    "brand": "",
    "qtys": [
      3,
      5,
      8,
      10,
      12,
      15
    ],
    "min_qty": 3,
    "volume": 0.0,
    "volume_unit": "L",
    "use_nobg": false,
    "draft": false,
    "gtin": "",
    "source_file": "하리보3.txt",
    "gosisi_cat": "기타 재화",
    "category_id": "",
    "category_is_manual": false,
    "qty_locked": false,
    "naver_price": 0,
    "manual_options": [],
    "lead_time": 10,
    "single_mode": false,
    "single_selected_imgs": [],
    "margin_override": 0.0,
    "watch_store": "제니스 트레이딩",
    "price_extra": 0,
    "extra_detail_images": [],
    "extra_detail_text": "",
    "status": "pending"
  },
  {
    "uid": "07824405",
    "url": "https://smartstore.naver.com/euromarkt/products/10972095221",
    "brand": "",
    "qtys": [
      3,
      5,
      8,
      10,
      12,
      15
    ],
    "min_qty": 3,
    "volume": 0.0,
    "volume_unit": "L",
    "use_nobg": false,
    "draft": false,
    "gtin": "",
    "source_file": "하리보3.txt",
    "gosisi_cat": "기타 재화",
    "category_id": "",
    "category_is_manual": false,
    "qty_locked": false,
    "naver_price": 0,
    "manual_options": [],
    "lead_time": 10,
    "single_mode": false,
    "single_selected_imgs": [],
    "margin_override": 0.0,
    "watch_store": "제니스 트레이딩",
    "price_extra": 0,
    "extra_detail_images": [],
    "extra_detail_text": "",
    "status": "pending"
  },
  {
    "uid": "22f74ac8",
    "url": "https://smartstore.naver.com/euromarkt/products/10972095144",
    "brand": "",
    "qtys": [
      3,
      5,
      8,
      10,
      12,
      15
    ],
    "min_qty": 3,
    "volume": 0.0,
    "volume_unit": "L",
    "use_nobg": false,
    "draft": false,
    "gtin": "",
    "source_file": "하리보3.txt",
    "gosisi_cat": "기타 재화",
    "category_id": "",
    "category_is_manual": false,
    "qty_locked": false,
    "naver_price": 0,
    "manual_options": [],
    "lead_time": 10,
    "single_mode": false,
    "single_selected_imgs": [],
    "margin_override": 0.0,
    "watch_store": "제니스 트레이딩",
    "price_extra": 0,
    "extra_detail_images": [],
    "extra_detail_text": "",
    "status": "pending"
  },
  {
    "uid": "5f288426",
    "url": "https://smartstore.naver.com/euromarkt/products/10305549816",
    "brand": "",
    "qtys": [
      3,
      5,
      8,
      10,
      12,
      15
    ],
    "min_qty": 3,
    "volume": 0.0,
    "volume_unit": "L",
    "use_nobg": false,
    "draft": false,
    "gtin": "",
    "source_file": "하리보3.txt",
    "gosisi_cat": "기타 재화",
    "category_id": "",
    "category_is_manual": false,
    "qty_locked": false,
    "naver_price": 0,
    "manual_options": [],
    "lead_time": 10,
    "single_mode": false,
    "single_selected_imgs": [],
    "margin_override": 0.0,
    "watch_store": "제니스 트레이딩",
    "price_extra": 0,
    "extra_detail_images": [],
    "extra_detail_text": "",
    "status": "pending"
  },
  {
    "uid": "26025ea9",
    "url": "https://smartstore.naver.com/euromarkt/products/9474286609",
    "brand": "",
    "qtys": [
      3,
      5,
      8,
      10,
      12,
      15
    ],
    "min_qty": 3,
    "volume": 0.0,
    "volume_unit": "L",
    "use_nobg": false,
    "draft": false,
    "gtin": "",
    "source_file": "하리보3.txt",
    "gosisi_cat": "기타 재화",
    "category_id": "",
    "category_is_manual": false,
    "qty_locked": false,
    "naver_price": 0,
    "manual_options": [],
    "lead_time": 10,
    "single_mode": false,
    "single_selected_imgs": [],
    "margin_override": 0.0,
    "watch_store": "제니스 트레이딩",
    "price_extra": 0,
    "extra_detail_images": [],
    "extra_detail_text": "",
    "status": "pending"
  },
  {
    "uid": "f68a8262",
    "url": "https://smartstore.naver.com/euromarkt/products/8670507666",
    "brand": "",
    "qtys": [
      3,
      5,
      8,
      10,
      12,
      15
    ],
    "min_qty": 3,
    "volume": 0.0,
    "volume_unit": "L",
    "use_nobg": false,
    "draft": false,
    "gtin": "",
    "source_file": "하리보3.txt",
    "gosisi_cat": "기타 재화",
    "category_id": "",
    "category_is_manual": false,
    "qty_locked": false,
    "naver_price": 0,
    "manual_options": [],
    "lead_time": 10,
    "single_mode": false,
    "single_selected_imgs": [],
    "margin_override": 0.0,
    "watch_store": "제니스 트레이딩",
    "price_extra": 0,
    "extra_detail_images": [],
    "extra_detail_text": "",
    "status": "pending"
  },
  {
    "uid": "bf4cae4d",
    "url": "https://smartstore.naver.com/euromarkt/products/8670505995",
    "brand": "",
    "qtys": [
      3,
      5,
      8,
      10,
      12,
      15
    ],
    "min_qty": 3,
    "volume": 0.0,
    "volume_unit": "L",
    "use_nobg": false,
    "draft": false,
    "gtin": "",
    "source_file": "하리보3.txt",
    "gosisi_cat": "기타 재화",
    "category_id": "",
    "category_is_manual": false,
    "qty_locked": false,
    "naver_price": 0,
    "manual_options": [],
    "lead_time": 10,
    "single_mode": false,
    "single_selected_imgs": [],
    "margin_override": 0.0,
    "watch_store": "제니스 트레이딩",
    "price_extra": 0,
    "extra_detail_images": [],
    "extra_detail_text": "",
    "status": "pending"
  },
  {
    "uid": "f35b68de",
    "url": "https://smartstore.naver.com/euromarkt/products/8670503613",
    "brand": "",
    "qtys": [
      3,
      5,
      8,
      10,
      12,
      15
    ],
    "min_qty": 3,
    "volume": 0.0,
    "volume_unit": "L",
    "use_nobg": false,
    "draft": false,
    "gtin": "",
    "source_file": "하리보3.txt",
    "gosisi_cat": "기타 재화",
    "category_id": "",
    "category_is_manual": false,
    "qty_locked": false,
    "naver_price": 0,
    "manual_options": [],
    "lead_time": 10,
    "single_mode": false,
    "single_selected_imgs": [],
    "margin_override": 0.0,
    "watch_store": "제니스 트레이딩",
    "price_extra": 0,
    "extra_detail_images": [],
    "extra_detail_text": "",
    "status": "pending"
  },
  {
    "uid": "9b8a0b33",
    "url": "https://smartstore.naver.com/euromarkt/products/8670501173",
    "brand": "",
    "qtys": [
      3,
      5,
      8,
      10,
      12,
      15
    ],
    "min_qty": 3,
    "volume": 0.0,
    "volume_unit": "L",
    "use_nobg": false,
    "draft": false,
    "gtin": "",
    "source_file": "하리보3.txt",
    "gosisi_cat": "기타 재화",
    "category_id": "",
    "category_is_manual": false,
    "qty_locked": false,
    "naver_price": 0,
    "manual_options": [],
    "lead_time": 10,
    "single_mode": false,
    "single_selected_imgs": [],
    "margin_override": 0.0,
    "watch_store": "제니스 트레이딩",
    "price_extra": 0,
    "extra_detail_images": [],
    "extra_detail_text": "",
    "status": "pending"
  },
  {
    "uid": "f5d2685f",
    "url": "https://smartstore.naver.com/euromarkt/products/8670491759",
    "brand": "",
    "qtys": [
      3,
      5,
      8,
      10,
      12,
      15
    ],
    "min_qty": 3,
    "volume": 0.0,
    "volume_unit": "L",
    "use_nobg": false,
    "draft": false,
    "gtin": "",
    "source_file": "하리보3.txt",
    "gosisi_cat": "기타 재화",
    "category_id": "",
    "category_is_manual": false,
    "qty_locked": false,
    "naver_price": 0,
    "manual_options": [],
    "lead_time": 10,
    "single_mode": false,
    "single_selected_imgs": [],
    "margin_override": 0.0,
    "watch_store": "제니스 트레이딩",
    "price_extra": 0,
    "extra_detail_images": [],
    "extra_detail_text": "",
    "status": "pending"
  },
  {
    "uid": "54dfaf32",
    "url": "https://smartstore.naver.com/euromarkt/products/8670488358",
    "brand": "",
    "qtys": [
      3,
      5,
      8,
      10,
      12,
      15
    ],
    "min_qty": 3,
    "volume": 0.0,
    "volume_unit": "L",
    "use_nobg": false,
    "draft": false,
    "gtin": "",
    "source_file": "하리보3.txt",
    "gosisi_cat": "기타 재화",
    "category_id": "",
    "category_is_manual": false,
    "qty_locked": false,
    "naver_price": 0,
    "manual_options": [],
    "lead_time": 10,
    "single_mode": false,
    "single_selected_imgs": [],
    "margin_override": 0.0,
    "watch_store": "제니스 트레이딩",
    "price_extra": 0,
    "extra_detail_images": [],
    "extra_detail_text": "",
    "status": "pending"
  },
  {
    "uid": "b0d97e25",
    "url": "https://smartstore.naver.com/euromarkt/products/8670484206",
    "brand": "",
    "qtys": [
      3,
      5,
      8,
      10,
      12,
      15
    ],
    "min_qty": 3,
    "volume": 0.0,
    "volume_unit": "L",
    "use_nobg": false,
    "draft": false,
    "gtin": "",
    "source_file": "하리보3.txt",
    "gosisi_cat": "기타 재화",
    "category_id": "",
    "category_is_manual": false,
    "qty_locked": false,
    "naver_price": 0,
    "manual_options": [],
    "lead_time": 10,
    "single_mode": false,
    "single_selected_imgs": [],
    "margin_override": 0.0,
    "watch_store": "제니스 트레이딩",
    "price_extra": 0,
    "extra_detail_images": [],
    "extra_detail_text": "",
    "status": "pending"
  },
  {
    "uid": "1b2ffd75",
    "url": "https://smartstore.naver.com/euromarkt/products/8670481545",
    "brand": "",
    "qtys": [
      3,
      5,
      8,
      10,
      12,
      15
    ],
    "min_qty": 3,
    "volume": 0.0,
    "volume_unit": "L",
    "use_nobg": false,
    "draft": false,
    "gtin": "",
    "source_file": "하리보3.txt",
    "gosisi_cat": "기타 재화",
    "category_id": "",
    "category_is_manual": false,
    "qty_locked": false,
    "naver_price": 0,
    "manual_options": [],
    "lead_time": 10,
    "single_mode": false,
    "single_selected_imgs": [],
    "margin_override": 0.0,
    "watch_store": "제니스 트레이딩",
    "price_extra": 0,
    "extra_detail_images": [],
    "extra_detail_text": "",
    "status": "pending"
  },
  {
    "uid": "01051914",
    "url": "https://smartstore.naver.com/euromarkt/products/8670479212",
    "brand": "",
    "qtys": [
      3,
      5,
      8,
      10,
      12,
      15
    ],
    "min_qty": 3,
    "volume": 0.0,
    "volume_unit": "L",
    "use_nobg": false,
    "draft": false,
    "gtin": "",
    "source_file": "하리보3.txt",
    "gosisi_cat": "기타 재화",
    "category_id": "",
    "category_is_manual": false,
    "qty_locked": false,
    "naver_price": 0,
    "manual_options": [],
    "lead_time": 10,
    "single_mode": false,
    "single_selected_imgs": [],
    "margin_override": 0.0,
    "watch_store": "제니스 트레이딩",
    "price_extra": 0,
    "extra_detail_images": [],
    "extra_detail_text": "",
    "status": "pending"
  },
  {
    "uid": "51f5636d",
    "url": "https://smartstore.naver.com/euromarkt/products/8670475723",
    "brand": "",
    "qtys": [
      3,
      5,
      8,
      10,
      12,
      15
    ],
    "min_qty": 3,
    "volume": 0.0,
    "volume_unit": "L",
    "use_nobg": false,
    "draft": false,
    "gtin": "",
    "source_file": "하리보3.txt",
    "gosisi_cat": "기타 재화",
    "category_id": "",
    "category_is_manual": false,
    "qty_locked": false,
    "naver_price": 0,
    "manual_options": [],
    "lead_time": 10,
    "single_mode": false,
    "single_selected_imgs": [],
    "margin_override": 0.0,
    "watch_store": "제니스 트레이딩",
    "price_extra": 0,
    "extra_detail_images": [],
    "extra_detail_text": "",
    "status": "pending"
  }
]